djlsum/__init__.py
djlsum/utils.py
djl_sum-0.0.1.dist-info/METADATA
djl_sum-0.0.1.dist-info/WHEEL
djl_sum-0.0.1.dist-info/top_level.txt
djl_sum-0.0.1.dist-info/RECORD
