Metadata-Version: 2.1
Name: djl-sum
Version: 0.0.1
Summary: UNKNOWN
Home-page: UNKNOWN
Author: deng jianlong
Author-email: jldeng3@163.com
License: UNKNOWN
Platform: UNKNOWN
Requires-Python: >=3
Requires-Dist: docutils (>=0.3)
